IDF/__init__.py
MAGE_Tab_merger-0.0.4.data/scripts/merge_baseline_configuration_xmls.py
MAGE_Tab_merger-0.0.4.data/scripts/merge_condensed_sdrfs.py
MAGE_Tab_merger-0.0.4.data/scripts/merge_data.py
MAGE_Tab_merger-0.0.4.data/scripts/merge_sdrfs.py
MAGE_Tab_merger-0.0.4.data/scripts/retrieve_data.py
SDRF/__init__.py
SDRF/sdrfcol_enum_tests.py
SDRF/tests.py
test_util/__init__.py
MAGE_Tab_merger-0.0.4.dist-info/METADATA
MAGE_Tab_merger-0.0.4.dist-info/WHEEL
MAGE_Tab_merger-0.0.4.dist-info/top_level.txt
MAGE_Tab_merger-0.0.4.dist-info/RECORD
