Metadata-Version: 2.1
Name: MAGE-Tab-merger
Version: 0.0.4
Summary: Merges MAGE-Tab files considering covariates
Home-page: UNKNOWN
Author: Pablo Moreno
Author-email: 
License: MIT
Platform: UNKNOWN
Requires-Dist: pandas
Requires-Dist: networkx (==2.5)
Requires-Dist: jinja2
Requires-Dist: requests
